{
  "openapi": "3.1.1",
  "info": {
    "title": "TradeDiary.Rotation | v1",
    "version": "1.0.0"
  },
  "servers": [
    {
      "url": "http://127.0.0.1:5608/"
    }
  ],
  "paths": {
    "/health/live": {
      "get": {
        "tags": [
          "TradeDiary.Rotation"
        ],
        "responses": {
          "200": {
            "description": "OK"
          }
        }
      }
    },
    "/health/ready": {
      "get": {
        "tags": [
          "TradeDiary.Rotation"
        ],
        "responses": {
          "200": {
            "description": "OK"
          }
        }
      }
    },
    "/version": {
      "get": {
        "tags": [
          "TradeDiary.Rotation"
        ],
        "responses": {
          "200": {
            "description": "OK"
          }
        }
      }
    },
    "/internal/rotation/universes": {
      "get": {
        "tags": [
          "TradeDiary.Rotation"
        ],
        "responses": {
          "200": {
            "description": "OK",
            "content": {
              "application/json": {
                "schema": {
                  "$ref": "#/components/schemas/CollectionResponseOfUniverseResponse"
                }
              }
            }
          }
        },
        "security": [
          {
            "bearerAuth": []
          }
        ]
      },
      "post": {
        "tags": [
          "TradeDiary.Rotation"
        ],
        "requestBody": {
          "content": {
            "application/json": {
              "schema": {
                "$ref": "#/components/schemas/UniverseWrite"
              }
            }
          },
          "required": true
        },
        "responses": {
          "201": {
            "description": "Created",
            "content": {
              "application/json": {
                "schema": {
                  "$ref": "#/components/schemas/UniverseCreatedResponse"
                }
              }
            }
          },
          "400": {
            "description": "Bad Request",
            "content": {
              "application/problem+json": {
                "schema": {
                  "$ref": "#/components/schemas/ProblemDetails"
                }
              }
            }
          },
          "409": {
            "description": "Conflict",
            "content": {
              "application/problem+json": {
                "schema": {
                  "$ref": "#/components/schemas/ProblemDetails"
                }
              }
            }
          }
        },
        "security": [
          {
            "bearerAuth": []
          }
        ]
      }
    },
    "/internal/rotation/universes/{id}": {
      "put": {
        "tags": [
          "TradeDiary.Rotation"
        ],
        "parameters": [
          {
            "name": "id",
            "in": "path",
            "required": true,
            "schema": {
              "type": "string",
              "format": "uuid"
            }
          }
        ],
        "requestBody": {
          "content": {
            "application/json": {
              "schema": {
                "$ref": "#/components/schemas/UniverseWrite"
              }
            }
          },
          "required": true
        },
        "responses": {
          "204": {
            "description": "No Content"
          },
          "400": {
            "description": "Bad Request",
            "content": {
              "application/problem+json": {
                "schema": {
                  "$ref": "#/components/schemas/ProblemDetails"
                }
              }
            }
          },
          "404": {
            "description": "Not Found",
            "content": {
              "application/problem+json": {
                "schema": {
                  "$ref": "#/components/schemas/ProblemDetails"
                }
              }
            }
          },
          "409": {
            "description": "Conflict",
            "content": {
              "application/problem+json": {
                "schema": {
                  "$ref": "#/components/schemas/ProblemDetails"
                }
              }
            }
          }
        },
        "security": [
          {
            "bearerAuth": []
          }
        ]
      },
      "delete": {
        "tags": [
          "TradeDiary.Rotation"
        ],
        "parameters": [
          {
            "name": "id",
            "in": "path",
            "required": true,
            "schema": {
              "type": "string",
              "format": "uuid"
            }
          }
        ],
        "responses": {
          "204": {
            "description": "No Content"
          },
          "404": {
            "description": "Not Found",
            "content": {
              "application/problem+json": {
                "schema": {
                  "$ref": "#/components/schemas/ProblemDetails"
                }
              }
            }
          }
        },
        "security": [
          {
            "bearerAuth": []
          }
        ]
      }
    },
    "/internal/rotation/universes/{id}/symbols": {
      "put": {
        "tags": [
          "TradeDiary.Rotation"
        ],
        "parameters": [
          {
            "name": "id",
            "in": "path",
            "required": true,
            "schema": {
              "type": "string",
              "format": "uuid"
            }
          }
        ],
        "requestBody": {
          "content": {
            "application/json": {
              "schema": {
                "type": "array",
                "items": {
                  "$ref": "#/components/schemas/UniverseSymbolWrite"
                }
              }
            }
          },
          "required": true
        },
        "responses": {
          "204": {
            "description": "No Content"
          },
          "400": {
            "description": "Bad Request",
            "content": {
              "application/problem+json": {
                "schema": {
                  "$ref": "#/components/schemas/ProblemDetails"
                }
              }
            }
          },
          "404": {
            "description": "Not Found",
            "content": {
              "application/problem+json": {
                "schema": {
                  "$ref": "#/components/schemas/ProblemDetails"
                }
              }
            }
          }
        },
        "security": [
          {
            "bearerAuth": []
          }
        ]
      }
    },
    "/internal/rotation/universes/{id}/calculate": {
      "post": {
        "tags": [
          "TradeDiary.Rotation"
        ],
        "parameters": [
          {
            "name": "id",
            "in": "path",
            "required": true,
            "schema": {
              "type": "string",
              "format": "uuid"
            }
          },
          {
            "name": "date",
            "in": "query",
            "required": true,
            "schema": {
              "type": "string",
              "format": "date"
            }
          }
        ],
        "responses": {
          "200": {
            "description": "OK",
            "content": {
              "application/json": {
                "schema": {
                  "$ref": "#/components/schemas/CalculateResponse"
                }
              }
            }
          },
          "404": {
            "description": "Not Found",
            "content": {
              "application/problem+json": {
                "schema": {
                  "$ref": "#/components/schemas/ProblemDetails"
                }
              }
            }
          }
        },
        "security": [
          {
            "bearerAuth": []
          }
        ]
      }
    },
    "/internal/rotation/monitor": {
      "get": {
        "tags": [
          "TradeDiary.Rotation"
        ],
        "parameters": [
          {
            "name": "universe",
            "in": "query",
            "required": true,
            "schema": {
              "type": "string"
            }
          },
          {
            "name": "date",
            "in": "query",
            "schema": {
              "type": "string",
              "format": "date"
            }
          }
        ],
        "responses": {
          "200": {
            "description": "OK",
            "content": {
              "application/json": {
                "schema": {
                  "$ref": "#/components/schemas/MonitorResponse"
                }
              }
            }
          },
          "404": {
            "description": "Not Found",
            "content": {
              "application/problem+json": {
                "schema": {
                  "$ref": "#/components/schemas/ProblemDetails"
                }
              }
            }
          }
        },
        "security": [
          {
            "bearerAuth": []
          }
        ]
      }
    }
  },
  "components": {
    "schemas": {
      "CalculateResponse": {
        "required": [
          "universeId",
          "snapshotDate",
          "status",
          "formulaVersion"
        ],
        "type": "object",
        "properties": {
          "universeId": {
            "type": "string",
            "format": "uuid"
          },
          "snapshotDate": {
            "type": "string",
            "format": "date"
          },
          "status": {
            "type": "string"
          },
          "formulaVersion": {
            "type": "string"
          }
        }
      },
      "CollectionResponseOfUniverseResponse": {
        "required": [
          "items"
        ],
        "type": "object",
        "properties": {
          "items": {
            "type": "array",
            "items": {
              "$ref": "#/components/schemas/UniverseResponse"
            }
          }
        }
      },
      "EtfSnapshotResponse": {
        "required": [
          "symbol",
          "label",
          "sector",
          "close",
          "return2w",
          "return1m",
          "return3m",
          "rank2w",
          "rankGroup",
          "percentile2w",
          "aboveMa20",
          "aboveMa50",
          "aboveMa200",
          "status"
        ],
        "type": "object",
        "properties": {
          "symbol": {
            "type": "string"
          },
          "label": {
            "type": "string"
          },
          "sector": {
            "type": [
              "null",
              "string"
            ]
          },
          "close": {
            "pattern": "^-?(?:0|[1-9]\\d*)(?:\\.\\d+)?$",
            "type": [
              "null",
              "number",
              "string"
            ],
            "format": "double"
          },
          "return2w": {
            "pattern": "^-?(?:0|[1-9]\\d*)(?:\\.\\d+)?$",
            "type": [
              "null",
              "number",
              "string"
            ],
            "format": "double"
          },
          "return1m": {
            "pattern": "^-?(?:0|[1-9]\\d*)(?:\\.\\d+)?$",
            "type": [
              "null",
              "number",
              "string"
            ],
            "format": "double"
          },
          "return3m": {
            "pattern": "^-?(?:0|[1-9]\\d*)(?:\\.\\d+)?$",
            "type": [
              "null",
              "number",
              "string"
            ],
            "format": "double"
          },
          "rank2w": {
            "pattern": "^-?(?:0|[1-9]\\d*)$",
            "type": [
              "null",
              "integer",
              "string"
            ],
            "format": "int32"
          },
          "rankGroup": {
            "type": "string"
          },
          "percentile2w": {
            "pattern": "^-?(?:0|[1-9]\\d*)(?:\\.\\d+)?$",
            "type": [
              "null",
              "number",
              "string"
            ],
            "format": "double"
          },
          "aboveMa20": {
            "type": [
              "null",
              "boolean"
            ]
          },
          "aboveMa50": {
            "type": [
              "null",
              "boolean"
            ]
          },
          "aboveMa200": {
            "type": [
              "null",
              "boolean"
            ]
          },
          "status": {
            "type": "string"
          }
        }
      },
      "MonitorMarketState": {
        "required": [
          "state",
          "breadthPercent",
          "benchmarkAboveMa200",
          "status"
        ],
        "type": "object",
        "properties": {
          "state": {
            "type": [
              "null",
              "string"
            ]
          },
          "breadthPercent": {
            "pattern": "^-?(?:0|[1-9]\\d*)(?:\\.\\d+)?$",
            "type": [
              "null",
              "number",
              "string"
            ],
            "format": "double"
          },
          "benchmarkAboveMa200": {
            "type": [
              "null",
              "boolean"
            ]
          },
          "status": {
            "type": "string"
          }
        }
      },
      "MonitorResponse": {
        "required": [
          "universe",
          "snapshotDate",
          "formulaVersion",
          "status",
          "marketState",
          "sectorBreadth",
          "etfs"
        ],
        "type": "object",
        "properties": {
          "universe": {
            "$ref": "#/components/schemas/MonitorUniverse"
          },
          "snapshotDate": {
            "type": [
              "null",
              "string"
            ],
            "format": "date"
          },
          "formulaVersion": {
            "type": "string"
          },
          "status": {
            "type": "string"
          },
          "marketState": {
            "$ref": "#/components/schemas/MonitorMarketState"
          },
          "sectorBreadth": {
            "type": "array",
            "items": {
              "$ref": "#/components/schemas/SectorBreadthResponse"
            }
          },
          "etfs": {
            "type": "array",
            "items": {
              "$ref": "#/components/schemas/EtfSnapshotResponse"
            }
          }
        }
      },
      "MonitorUniverse": {
        "required": [
          "id",
          "code",
          "name",
          "rankScope"
        ],
        "type": "object",
        "properties": {
          "id": {
            "type": "string",
            "format": "uuid"
          },
          "code": {
            "type": "string"
          },
          "name": {
            "type": "string"
          },
          "rankScope": {
            "type": "string"
          }
        }
      },
      "ProblemDetails": {
        "type": "object",
        "properties": {
          "type": {
            "type": [
              "null",
              "string"
            ]
          },
          "title": {
            "type": [
              "null",
              "string"
            ]
          },
          "status": {
            "pattern": "^-?(?:0|[1-9]\\d*)$",
            "type": [
              "null",
              "integer",
              "string"
            ],
            "format": "int32"
          },
          "detail": {
            "type": [
              "null",
              "string"
            ]
          },
          "instance": {
            "type": [
              "null",
              "string"
            ]
          }
        }
      },
      "SectorBreadthResponse": {
        "required": [
          "sector",
          "memberCount",
          "availableCount",
          "aboveMa20Percent",
          "aboveMa50Percent",
          "aboveMa200Percent",
          "status"
        ],
        "type": "object",
        "properties": {
          "sector": {
            "type": "string"
          },
          "memberCount": {
            "pattern": "^-?(?:0|[1-9]\\d*)$",
            "type": [
              "integer",
              "string"
            ],
            "format": "int32"
          },
          "availableCount": {
            "pattern": "^-?(?:0|[1-9]\\d*)$",
            "type": [
              "integer",
              "string"
            ],
            "format": "int32"
          },
          "aboveMa20Percent": {
            "pattern": "^-?(?:0|[1-9]\\d*)(?:\\.\\d+)?$",
            "type": [
              "null",
              "number",
              "string"
            ],
            "format": "double"
          },
          "aboveMa50Percent": {
            "pattern": "^-?(?:0|[1-9]\\d*)(?:\\.\\d+)?$",
            "type": [
              "null",
              "number",
              "string"
            ],
            "format": "double"
          },
          "aboveMa200Percent": {
            "pattern": "^-?(?:0|[1-9]\\d*)(?:\\.\\d+)?$",
            "type": [
              "null",
              "number",
              "string"
            ],
            "format": "double"
          },
          "status": {
            "type": "string"
          }
        }
      },
      "UniverseCreatedResponse": {
        "required": [
          "id",
          "code",
          "name",
          "rankScope"
        ],
        "type": "object",
        "properties": {
          "id": {
            "type": "string",
            "format": "uuid"
          },
          "code": {
            "type": "string"
          },
          "name": {
            "type": "string"
          },
          "rankScope": {
            "type": "string"
          }
        }
      },
      "UniverseResponse": {
        "required": [
          "id",
          "code",
          "name",
          "rankScope",
          "createdAt",
          "updatedAt"
        ],
        "type": "object",
        "properties": {
          "id": {
            "type": "string",
            "format": "uuid"
          },
          "code": {
            "type": "string"
          },
          "name": {
            "type": "string"
          },
          "rankScope": {
            "type": "string"
          },
          "createdAt": {
            "type": "string",
            "format": "date-time"
          },
          "updatedAt": {
            "type": "string",
            "format": "date-time"
          }
        }
      },
      "UniverseSymbolWrite": {
        "required": [
          "symbol",
          "label",
          "sector",
          "sortOrder"
        ],
        "type": "object",
        "properties": {
          "symbol": {
            "type": "string"
          },
          "label": {
            "type": "string"
          },
          "sector": {
            "type": [
              "null",
              "string"
            ]
          },
          "sortOrder": {
            "pattern": "^-?(?:0|[1-9]\\d*)$",
            "type": [
              "null",
              "integer",
              "string"
            ],
            "format": "int32"
          }
        }
      },
      "UniverseWrite": {
        "required": [
          "code",
          "name",
          "rankScope"
        ],
        "type": "object",
        "properties": {
          "code": {
            "type": "string"
          },
          "name": {
            "type": "string"
          },
          "rankScope": {
            "type": [
              "null",
              "string"
            ]
          }
        }
      }
    },
    "securitySchemes": {
      "bearerAuth": {
        "type": "http",
        "scheme": "bearer",
        "bearerFormat": "JWT"
      },
      "serviceKey": {
        "type": "apiKey",
        "name": "X-Service-Key",
        "in": "header"
      }
    }
  },
  "tags": [
    {
      "name": "TradeDiary.Rotation"
    }
  ]
}
